spotify_client/__init__.py
spotify_client/client.py
spotify_client/config.py
spotify_client/exceptions.py
tests/__init__.py
tests/test_config.py
tests/test_spotify_client.py
spotify_client-1.9.1.dist-info/LICENSE
spotify_client-1.9.1.dist-info/METADATA
spotify_client-1.9.1.dist-info/WHEEL
spotify_client-1.9.1.dist-info/top_level.txt
spotify_client-1.9.1.dist-info/RECORD
