Metadata-Version: 2.1
Name: spotify-client
Version: 1.9.1
Summary: Client for interacting with the Spotify API
Home-page: https://github.com/Moody-Tunes/spotify-client
Author: MoodyTunes
Author-email: moody.tunes.infrastucture@gmail.com
License: UNKNOWN
Platform: UNKNOWN
Classifier: Programming Language :: Python :: 3
Classifier: License :: OSI Approved :: MIT License
Classifier: Operating System :: OS Independent
Requires-Python: >=3.6
